{"data": [{"project name": "Converting to text file", "destination type": "TXT", "connection string": "C:/Users/dranh/Desktop/Log.txt", "is initialized": true, "destination schema": {"AAA": "integer", "BBB": "float", "Column 2": "string"}, "data sources": [{"type": "CSV", "connection string": "", "schema": {}, "mapping": {}}, {"type": "EXCEL", "connection string": "", "schema": {}, "mapping": {}}, {"type": "CSV", "connection string": "", "schema": {}, "mapping": {}}], "id": 702532011787352013}, {"project name": "Test txt", "destination type": "TXT", "connection string": null, "is initialized": false, "destination schema": null, "data sources": [], "id": 253808362936228045}]}